ort/__init__.py
ort/models/__init__.py
ort/models/analyzer_result.py
ort/models/analyzer_run.py
ort/models/config/analyzer_configuration.py
ort/models/config/curations.py
ort/models/config/license_finding_curation.py
ort/models/config/license_finding_curation_reason.py
ort/models/config/package_configuration.py
ort/models/config/package_manager_configuration.py
ort/models/config/path_exclude.py
ort/models/config/path_exclude_reason.py
ort/models/config/path_include_reason.py
ort/models/config/repository_analyzer_configuration.py
ort/models/config/vcsmatcher.py
ort/models/dependency_graph.py
ort/models/dependency_graph_edge.py
ort/models/dependency_graph_node.py
ort/models/dependency_reference.py
ort/models/hash.py
ort/models/hash_algorithm.py
ort/models/identifier.py
ort/models/issue.py
ort/models/ort_result.py
ort/models/package.py
ort/models/package_curation.py
ort/models/package_curation_data.py
ort/models/package_linkage.py
ort/models/package_reference.py
ort/models/project.py
ort/models/remote_artifact.py
ort/models/repository.py
ort/models/repository_configuration.py
ort/models/resolutions.py
ort/models/root_dependency_index.py
ort/models/scope.py
ort/models/source_code_origin.py
ort/models/vcsinfo.py
ort/models/vcsinfo_curation_data.py
ort/models/vcstype.py
ort/severity.py
ort/utils/__init__.py
ort/utils/environment.py
ort/utils/processed_declared_license.py
python_ort-0.5.0.dist-info/licenses/LICENSE
python_ort-0.5.0.dist-info/WHEEL
python_ort-0.5.0.dist-info/METADATA
python_ort-0.5.0.dist-info/RECORD
